dist
ib1
lib
