Metadata-Version: 2.1
Name: ib1.openenergy.support
Version: 0.2.16
Summary: Tools, and Flask and Requests extensions, to support data providers and clients within the open energy ecosystem
Home-page: https://github.com/icebreakerone/open-energy-python-infrastructure
Author: Tom Oinn
Author-email: tom.oinn@icebreakerone.org
License: UNKNOWN
Platform: UNKNOWN
Classifier: Programming Language :: Python :: 3.7
Classifier: Development Status :: 4 - Beta
Classifier: Framework :: Flask
Classifier: License :: OSI Approved :: MIT License
Classifier: Topic :: Security
Classifier: Topic :: Scientific/Engineering
